sensor_position_dataset_helper/__init__.py
sensor_position_dataset_helper/consts.py
sensor_position_dataset_helper/helper.py
sensor_position_dataset_helper/internal_helpers.py
sensor_position_dataset_helper/tpcp_dataset.py
sensor_position_dataset_helper/utils.py
sensor_position_dataset_helper/zeni_event_detection.py
sensor_position_dataset_helper-1.2.0.dist-info/LICENSE
sensor_position_dataset_helper-1.2.0.dist-info/WHEEL
sensor_position_dataset_helper-1.2.0.dist-info/METADATA
sensor_position_dataset_helper-1.2.0.dist-info/RECORD
