Metadata-Version: 2.1
Name: sensor-position-dataset-helper
Version: 1.2.0
Summary: A helper for the SensorPositionDateset (recorded 2019, published 2021)
Home-page: https://github.com/mad-lab-fau/sensor_position_dataset_helper
License: MIT
Author: Arne Küderle
Author-email: arne.kuederle@fau.de
Requires-Python: >=3.7.1,<3.11
Classifier: License :: OSI Approved :: MIT License
Classifier: Programming Language :: Python :: 3
Classifier: Programming Language :: Python :: 3.10
Classifier: Programming Language :: Python :: 3.8
Classifier: Programming Language :: Python :: 3.9
Requires-Dist: GitPython (>=3.1.13,<4.0.0)
Requires-Dist: c3d (>=0.3.0,<0.4.0)
Requires-Dist: imucal (>=2.0.0,<3.0.0)
Requires-Dist: joblib (>=1.0.0,<2.0.0)
Requires-Dist: nilspodlib (>=3.1,<4.0)
Requires-Dist: numpy (>=1.20.0,<2.0.0)
Requires-Dist: pandas (>=1.2.2,<2.0.0)
Requires-Dist: scipy (>=1,<2)
Requires-Dist: tpcp (>=0.3.1)
Requires-Dist: typing-extensions (>=3.7.4)
Project-URL: Repository, https://github.com/mad-lab-fau/sensor_position_dataset_helper
